gaussian_renderer/__init__.py
gaussian_renderer/batch_splat.py
gaussian_renderer/gs_renderer_motrixsim.py
gaussian_renderer/gs_renderer_mujoco.py
gaussian_renderer/simple_viewer.py
gaussian_renderer/supersplat_compress.py
gaussian_renderer/transform_gs_model.py
gaussian_renderer/src/__init__.py
gaussian_renderer/src/batch_rasterization.py
gaussian_renderer/src/gaussiandata.py
gaussian_renderer/src/gs_renderer.py
gaussian_renderer/src/super_splat_loader.py
gaussian_renderer/src/util_gau.py
gaussian_renderer-0.1.8.dist-info/licenses/LICENSE
gaussian_renderer-0.1.8.dist-info/METADATA
gaussian_renderer-0.1.8.dist-info/WHEEL
gaussian_renderer-0.1.8.dist-info/entry_points.txt
gaussian_renderer-0.1.8.dist-info/top_level.txt
gaussian_renderer-0.1.8.dist-info/RECORD
