Metadata-Version: 2.4
Name: gaussian_renderer
Version: 0.1.8
Summary: A Gaussian Splatting Renderer and Tools
Requires-Python: >=3.8
License-File: LICENSE
Requires-Dist: numpy
Requires-Dist: torch
Requires-Dist: scipy
Requires-Dist: plyfile
Requires-Dist: trimesh
Requires-Dist: gsplat
Provides-Extra: viewer
Requires-Dist: glfw; extra == "viewer"
Requires-Dist: PyOpenGL; extra == "viewer"
Provides-Extra: motrix
Requires-Dist: motrixsim>=0.5.0; extra == "motrix"
Provides-Extra: mujoco
Requires-Dist: mujoco; extra == "mujoco"
Dynamic: license-file
